Workbook

Sheet Supuestos
A1: Supuesto | B1: Valor | C1: Unidad | D1: Tipo | E1: De dónde sale | F1: Rango posible
A2: Personas en el área de influencia | B2: 50000 | C2: personas | D2: Supuesto | E2: Inventado para el ejercicio, sin evidencia. Reemplazar por cifra del DANE o del propietario | F2: 0.25
A3: Captura por día abierto | B3: 0.001 | C3: % de las personas del área, por día abierto | D3: Supuesto | E3: Inventado: 1 de cada 1.000 personas del área visita en un día abierto. Sin evidencia | F3: 0.5
A4: Precio por persona | B4: 45000 | C4: pesos por persona | D4: Supuesto | E4: Inventado: gasto promedio por persona, por comprobar con ventas reales | F4: 0.1
A5: Costo por cliente | B5: 18000 | C5: pesos por persona | D5: Supuesto | E5: Inventado: bebidas y comida, 40 % del gasto promedio | F5: 0.1
A6: Costos fijos adicionales al mes | B6: 9000000 | C6: pesos al mes | D6: Supuesto | E6: Inventado: personal de barra, cocina y seguridad, energía y música de los días extra | F6: 0.1
A7: Patrón de días abiertos entre semana | B7: 1100111 | C7: texto: lunes a domingo, 1 = cerrado, 0 = abierto | D7: Supuesto | E7: Decisión del caso: abrir miércoles y jueves | F7: 0
A8: Variación de demanda, escenario pesimista | B8: -0.3 | C8: % frente al caso base | D8: Supuesto | E8: Inventado: entre semana se llena 30 % menos de lo esperado | F8: 0
A9: Variación de demanda, escenario base | B9: 0 | C9: % frente al caso base | D9: Supuesto | E9: Caso base, sin cambio | F9: 0
A10: Variación de demanda, escenario optimista | B10: 0.2 | C10: % frente al caso base | D10: Supuesto | E10: Inventado: entre semana se llena 20 % más de lo esperado | F10: 0

Sheet Cálculo
A1: Mes | B1: Días abiertos | C1: Clientes | D1: Ingresos | E1: Costos variables | F1: Costos fijos | G1: Utilidad | H1: Utilidad acumulada
A2: Enero | B2: =NETWORKDAYS.INTL(DATE(2027,1,1),EOMONTH(DATE(2027,1,1),0),Supuestos!$B$7) -> 8 | C2: =ROUND(B2*Supuestos!$B$2*Supuestos!$B$3,0) -> 400 | D2: =C2*Supuestos!$B$4 -> 18000000 | E2: =C2*Supuestos!$B$5 -> 7200000 | F2: =Supuestos!$B$6 -> 9000000 | G2: =D2-E2-F2 -> 1800000 | H2: =SUM($G$2:G2) -> 1800000
A3: Febrero | B3: =NETWORKDAYS.INTL(DATE(2027,2,1),EOMONTH(DATE(2027,2,1),0),Supuestos!$B$7) -> 8 | C3: =ROUND(B3*Supuestos!$B$2*Supuestos!$B$3,0) -> 400 | D3: =C3*Supuestos!$B$4 -> 18000000 | E3: =C3*Supuestos!$B$5 -> 7200000 | F3: =Supuestos!$B$6 -> 9000000 | G3: =D3-E3-F3 -> 1800000 | H3: =SUM($G$2:G3) -> 3600000
A4: Marzo | B4: =NETWORKDAYS.INTL(DATE(2027,3,1),EOMONTH(DATE(2027,3,1),0),Supuestos!$B$7) -> 9 | C4: =ROUND(B4*Supuestos!$B$2*Supuestos!$B$3,0) -> 450 | D4: =C4*Supuestos!$B$4 -> 20250000 | E4: =C4*Supuestos!$B$5 -> 8100000 | F4: =Supuestos!$B$6 -> 9000000 | G4: =D4-E4-F4 -> 3150000 | H4: =SUM($G$2:G4) -> 6750000
A5: Abril | B5: =NETWORKDAYS.INTL(DATE(2027,4,1),EOMONTH(DATE(2027,4,1),0),Supuestos!$B$7) -> 9 | C5: =ROUND(B5*Supuestos!$B$2*Supuestos!$B$3,0) -> 450 | D5: =C5*Supuestos!$B$4 -> 20250000 | E5: =C5*Supuestos!$B$5 -> 8100000 | F5: =Supuestos!$B$6 -> 9000000 | G5: =D5-E5-F5 -> 3150000 | H5: =SUM($G$2:G5) -> 9900000
A6: Mayo | B6: =NETWORKDAYS.INTL(DATE(2027,5,1),EOMONTH(DATE(2027,5,1),0),Supuestos!$B$7) -> 8 | C6: =ROUND(B6*Supuestos!$B$2*Supuestos!$B$3,0) -> 400 | D6: =C6*Supuestos!$B$4 -> 18000000 | E6: =C6*Supuestos!$B$5 -> 7200000 | F6: =Supuestos!$B$6 -> 9000000 | G6: =D6-E6-F6 -> 1800000 | H6: =SUM($G$2:G6) -> 11700000
A7: Junio | B7: =NETWORKDAYS.INTL(DATE(2027,6,1),EOMONTH(DATE(2027,6,1),0),Supuestos!$B$7) -> 9 | C7: =ROUND(B7*Supuestos!$B$2*Supuestos!$B$3,0) -> 450 | D7: =C7*Supuestos!$B$4 -> 20250000 | E7: =C7*Supuestos!$B$5 -> 8100000 | F7: =Supuestos!$B$6 -> 9000000 | G7: =D7-E7-F7 -> 3150000 | H7: =SUM($G$2:G7) -> 14850000
A8: Julio | B8: =NETWORKDAYS.INTL(DATE(2027,7,1),EOMONTH(DATE(2027,7,1),0),Supuestos!$B$7) -> 9 | C8: =ROUND(B8*Supuestos!$B$2*Supuestos!$B$3,0) -> 450 | D8: =C8*Supuestos!$B$4 -> 20250000 | E8: =C8*Supuestos!$B$5 -> 8100000 | F8: =Supuestos!$B$6 -> 9000000 | G8: =D8-E8-F8 -> 3150000 | H8: =SUM($G$2:G8) -> 18000000
A9: Agosto | B9: =NETWORKDAYS.INTL(DATE(2027,8,1),EOMONTH(DATE(2027,8,1),0),Supuestos!$B$7) -> 8 | C9: =ROUND(B9*Supuestos!$B$2*Supuestos!$B$3,0) -> 400 | D9: =C9*Supuestos!$B$4 -> 18000000 | E9: =C9*Supuestos!$B$5 -> 7200000 | F9: =Supuestos!$B$6 -> 9000000 | G9: =D9-E9-F9 -> 1800000 | H9: =SUM($G$2:G9) -> 19800000
A10: Septiembre | B10: =NETWORKDAYS.INTL(DATE(2027,9,1),EOMONTH(DATE(2027,9,1),0),Supuestos!$B$7) -> 10 | C10: =ROUND(B10*Supuestos!$B$2*Supuestos!$B$3,0) -> 500 | D10: =C10*Supuestos!$B$4 -> 22500000 | E10: =C10*Supuestos!$B$5 -> 9000000 | F10: =Supuestos!$B$6 -> 9000000 | G10: =D10-E10-F10 -> 4500000 | H10: =SUM($G$2:G10) -> 24300000
A11: Octubre | B11: =NETWORKDAYS.INTL(DATE(2027,10,1),EOMONTH(DATE(2027,10,1),0),Supuestos!$B$7) -> 8 | C11: =ROUND(B11*Supuestos!$B$2*Supuestos!$B$3,0) -> 400 | D11: =C11*Supuestos!$B$4 -> 18000000 | E11: =C11*Supuestos!$B$5 -> 7200000 | F11: =Supuestos!$B$6 -> 9000000 | G11: =D11-E11-F11 -> 1800000 | H11: =SUM($G$2:G11) -> 26100000
A12: Noviembre | B12: =NETWORKDAYS.INTL(DATE(2027,11,1),EOMONTH(DATE(2027,11,1),0),Supuestos!$B$7) -> 8 | C12: =ROUND(B12*Supuestos!$B$2*Supuestos!$B$3,0) -> 400 | D12: =C12*Supuestos!$B$4 -> 18000000 | E12: =C12*Supuestos!$B$5 -> 7200000 | F12: =Supuestos!$B$6 -> 9000000 | G12: =D12-E12-F12 -> 1800000 | H12: =SUM($G$2:G12) -> 27900000
A13: Diciembre | B13: =NETWORKDAYS.INTL(DATE(2027,12,1),EOMONTH(DATE(2027,12,1),0),Supuestos!$B$7) -> 10 | C13: =ROUND(B13*Supuestos!$B$2*Supuestos!$B$3,0) -> 500 | D13: =C13*Supuestos!$B$4 -> 22500000 | E13: =C13*Supuestos!$B$5 -> 9000000 | F13: =Supuestos!$B$6 -> 9000000 | G13: =D13-E13-F13 -> 4500000 | H13: =SUM($G$2:G13) -> 32400000
A14: Total | B14: =SUM(B2:B13) -> 104 | C14: =SUM(C2:C13) -> 5200 | D14: =SUM(D2:D13) -> 234000000 | E14: =SUM(E2:E13) -> 93600000 | F14: =SUM(F2:F13) -> 108000000 | G14: =SUM(G2:G13) -> 32400000
A16: Punto de equilibrio (clientes al mes) | B16: =Supuestos!B6/(Supuestos!B4-Supuestos!B5) -> 333.33333
A17: Meses con pérdida | B17: =COUNTIF(G2:G13,"<0") -> 0
A18: Reserva necesaria | B18: =MAX(0,-MIN(H2:H13)) -> 0
A19: Captura de equilibrio (% de las personas del área, por día abierto) | B19: =(Supuestos!B6*12/(Supuestos!B4-Supuestos!B5))/(B14*Supuestos!B2) -> 0.00076923077

Sheet Escenarios
A1: Mes | B1: Pesimista | C1: Base | D1: Optimista | E1: Acum. pesimista | F1: Acum. base | G1: Acum. optimista
A2: Enero | B2: =ROUND(Cálculo!$B2*Supuestos!$B$2*Supuestos!$B$3*(1+B$17),0)*(Supuestos!$B$4-Supuestos!$B$5)-Supuestos!$B$6 -> -1440000 | C2: =ROUND(Cálculo!$B2*Supuestos!$B$2*Supuestos!$B$3*(1+C$17),0)*(Supuestos!$B$4-Supuestos!$B$5)-Supuestos!$B$6 -> 1800000 | D2: =ROUND(Cálculo!$B2*Supuestos!$B$2*Supuestos!$B$3*(1+D$17),0)*(Supuestos!$B$4-Supuestos!$B$5)-Supuestos!$B$6 -> 3960000 | E2: =SUM(B$2:B2) -> -1440000 | F2: =SUM(C$2:C2) -> 1800000 | G2: =SUM(D$2:D2) -> 3960000
A3: Febrero | B3: =ROUND(Cálculo!$B3*Supuestos!$B$2*Supuestos!$B$3*(1+B$17),0)*(Supuestos!$B$4-Supuestos!$B$5)-Supuestos!$B$6 -> -1440000 | C3: =ROUND(Cálculo!$B3*Supuestos!$B$2*Supuestos!$B$3*(1+C$17),0)*(Supuestos!$B$4-Supuestos!$B$5)-Supuestos!$B$6 -> 1800000 | D3: =ROUND(Cálculo!$B3*Supuestos!$B$2*Supuestos!$B$3*(1+D$17),0)*(Supuestos!$B$4-Supuestos!$B$5)-Supuestos!$B$6 -> 3960000 | E3: =SUM(B$2:B3) -> -2880000 | F3: =SUM(C$2:C3) -> 3600000 | G3: =SUM(D$2:D3) -> 7920000
A4: Marzo | B4: =ROUND(Cálculo!$B4*Supuestos!$B$2*Supuestos!$B$3*(1+B$17),0)*(Supuestos!$B$4-Supuestos!$B$5)-Supuestos!$B$6 -> -495000 | C4: =ROUND(Cálculo!$B4*Supuestos!$B$2*Supuestos!$B$3*(1+C$17),0)*(Supuestos!$B$4-Supuestos!$B$5)-Supuestos!$B$6 -> 3150000 | D4: =ROUND(Cálculo!$B4*Supuestos!$B$2*Supuestos!$B$3*(1+D$17),0)*(Supuestos!$B$4-Supuestos!$B$5)-Supuestos!$B$6 -> 5580000 | E4: =SUM(B$2:B4) -> -3375000 | F4: =SUM(C$2:C4) -> 6750000 | G4: =SUM(D$2:D4) -> 13500000
A5: Abril | B5: =ROUND(Cálculo!$B5*Supuestos!$B$2*Supuestos!$B$3*(1+B$17),0)*(Supuestos!$B$4-Supuestos!$B$5)-Supuestos!$B$6 -> -495000 | C5: =ROUND(Cálculo!$B5*Supuestos!$B$2*Supuestos!$B$3*(1+C$17),0)*(Supuestos!$B$4-Supuestos!$B$5)-Supuestos!$B$6 -> 3150000 | D5: =ROUND(Cálculo!$B5*Supuestos!$B$2*Supuestos!$B$3*(1+D$17),0)*(Supuestos!$B$4-Supuestos!$B$5)-Supuestos!$B$6 -> 5580000 | E5: =SUM(B$2:B5) -> -3870000 | F5: =SUM(C$2:C5) -> 9900000 | G5: =SUM(D$2:D5) -> 19080000
A6: Mayo | B6: =ROUND(Cálculo!$B6*Supuestos!$B$2*Supuestos!$B$3*(1+B$17),0)*(Supuestos!$B$4-Supuestos!$B$5)-Supuestos!$B$6 -> -1440000 | C6: =ROUND(Cálculo!$B6*Supuestos!$B$2*Supuestos!$B$3*(1+C$17),0)*(Supuestos!$B$4-Supuestos!$B$5)-Supuestos!$B$6 -> 1800000 | D6: =ROUND(Cálculo!$B6*Supuestos!$B$2*Supuestos!$B$3*(1+D$17),0)*(Supuestos!$B$4-Supuestos!$B$5)-Supuestos!$B$6 -> 3960000 | E6: =SUM(B$2:B6) -> -5310000 | F6: =SUM(C$2:C6) -> 11700000 | G6: =SUM(D$2:D6) -> 23040000
A7: Junio | B7: =ROUND(Cálculo!$B7*Supuestos!$B$2*Supuestos!$B$3*(1+B$17),0)*(Supuestos!$B$4-Supuestos!$B$5)-Supuestos!$B$6 -> -495000 | C7: =ROUND(Cálculo!$B7*Supuestos!$B$2*Supuestos!$B$3*(1+C$17),0)*(Supuestos!$B$4-Supuestos!$B$5)-Supuestos!$B$6 -> 3150000 | D7: =ROUND(Cálculo!$B7*Supuestos!$B$2*Supuestos!$B$3*(1+D$17),0)*(Supuestos!$B$4-Supuestos!$B$5)-Supuestos!$B$6 -> 5580000 | E7: =SUM(B$2:B7) -> -5805000 | F7: =SUM(C$2:C7) -> 14850000 | G7: =SUM(D$2:D7) -> 28620000
A8: Julio | B8: =ROUND(Cálculo!$B8*Supuestos!$B$2*Supuestos!$B$3*(1+B$17),0)*(Supuestos!$B$4-Supuestos!$B$5)-Supuestos!$B$6 -> -495000 | C8: =ROUND(Cálculo!$B8*Supuestos!$B$2*Supuestos!$B$3*(1+C$17),0)*(Supuestos!$B$4-Supuestos!$B$5)-Supuestos!$B$6 -> 3150000 | D8: =ROUND(Cálculo!$B8*Supuestos!$B$2*Supuestos!$B$3*(1+D$17),0)*(Supuestos!$B$4-Supuestos!$B$5)-Supuestos!$B$6 -> 5580000 | E8: =SUM(B$2:B8) -> -6300000 | F8: =SUM(C$2:C8) -> 18000000 | G8: =SUM(D$2:D8) -> 34200000
A9: Agosto | B9: =ROUND(Cálculo!$B9*Supuestos!$B$2*Supuestos!$B$3*(1+B$17),0)*(Supuestos!$B$4-Supuestos!$B$5)-Supuestos!$B$6 -> -1440000 | C9: =ROUND(Cálculo!$B9*Supuestos!$B$2*Supuestos!$B$3*(1+C$17),0)*(Supuestos!$B$4-Supuestos!$B$5)-Supuestos!$B$6 -> 1800000 | D9: =ROUND(Cálculo!$B9*Supuestos!$B$2*Supuestos!$B$3*(1+D$17),0)*(Supuestos!$B$4-Supuestos!$B$5)-Supuestos!$B$6 -> 3960000 | E9: =SUM(B$2:B9) -> -7740000 | F9: =SUM(C$2:C9) -> 19800000 | G9: =SUM(D$2:D9) -> 38160000
A10: Septiembre | B10: =ROUND(Cálculo!$B10*Supuestos!$B$2*Supuestos!$B$3*(1+B$17),0)*(Supuestos!$B$4-Supuestos!$B$5)-Supuestos!$B$6 -> 450000 | C10: =ROUND(Cálculo!$B10*Supuestos!$B$2*Supuestos!$B$3*(1+C$17),0)*(Supuestos!$B$4-Supuestos!$B$5)-Supuestos!$B$6 -> 4500000 | D10: =ROUND(Cálculo!$B10*Supuestos!$B$2*Supuestos!$B$3*(1+D$17),0)*(Supuestos!$B$4-Supuestos!$B$5)-Supuestos!$B$6 -> 7200000 | E10: =SUM(B$2:B10) -> -7290000 | F10: =SUM(C$2:C10) -> 24300000 | G10: =SUM(D$2:D10) -> 45360000
A11: Octubre | B11: =ROUND(Cálculo!$B11*Supuestos!$B$2*Supuestos!$B$3*(1+B$17),0)*(Supuestos!$B$4-Supuestos!$B$5)-Supuestos!$B$6 -> -1440000 | C11: =ROUND(Cálculo!$B11*Supuestos!$B$2*Supuestos!$B$3*(1+C$17),0)*(Supuestos!$B$4-Supuestos!$B$5)-Supuestos!$B$6 -> 1800000 | D11: =ROUND(Cálculo!$B11*Supuestos!$B$2*Supuestos!$B$3*(1+D$17),0)*(Supuestos!$B$4-Supuestos!$B$5)-Supuestos!$B$6 -> 3960000 | E11: =SUM(B$2:B11) -> -8730000 | F11: =SUM(C$2:C11) -> 26100000 | G11: =SUM(D$2:D11) -> 49320000
A12: Noviembre | B12: =ROUND(Cálculo!$B12*Supuestos!$B$2*Supuestos!$B$3*(1+B$17),0)*(Supuestos!$B$4-Supuestos!$B$5)-Supuestos!$B$6 -> -1440000 | C12: =ROUND(Cálculo!$B12*Supuestos!$B$2*Supuestos!$B$3*(1+C$17),0)*(Supuestos!$B$4-Supuestos!$B$5)-Supuestos!$B$6 -> 1800000 | D12: =ROUND(Cálculo!$B12*Supuestos!$B$2*Supuestos!$B$3*(1+D$17),0)*(Supuestos!$B$4-Supuestos!$B$5)-Supuestos!$B$6 -> 3960000 | E12: =SUM(B$2:B12) -> -10170000 | F12: =SUM(C$2:C12) -> 27900000 | G12: =SUM(D$2:D12) -> 53280000
A13: Diciembre | B13: =ROUND(Cálculo!$B13*Supuestos!$B$2*Supuestos!$B$3*(1+B$17),0)*(Supuestos!$B$4-Supuestos!$B$5)-Supuestos!$B$6 -> 450000 | C13: =ROUND(Cálculo!$B13*Supuestos!$B$2*Supuestos!$B$3*(1+C$17),0)*(Supuestos!$B$4-Supuestos!$B$5)-Supuestos!$B$6 -> 4500000 | D13: =ROUND(Cálculo!$B13*Supuestos!$B$2*Supuestos!$B$3*(1+D$17),0)*(Supuestos!$B$4-Supuestos!$B$5)-Supuestos!$B$6 -> 7200000 | E13: =SUM(B$2:B13) -> -9720000 | F13: =SUM(C$2:C13) -> 32400000 | G13: =SUM(D$2:D13) -> 60480000
A14: Utilidad del año | B14: =SUM(B2:B13) -> -9720000 | C14: =SUM(C2:C13) -> 32400000 | D14: =SUM(D2:D13) -> 60480000
A15: Meses con pérdida | B15: =COUNTIF(B2:B13,"<0") -> 10 | C15: =COUNTIF(C2:C13,"<0") -> 0 | D15: =COUNTIF(D2:D13,"<0") -> 0
A16: Reserva necesaria | B16: =MAX(0,-MIN(E2:E13)) -> 10170000 | C16: =MAX(0,-MIN(F2:F13)) -> 0 | D16: =MAX(0,-MIN(G2:G13)) -> 0
A17: Variación de demanda | B17: =Supuestos!B8 -> -0.3 | C17: =Supuestos!B9 -> 0 | D17: =Supuestos!B10 -> 0.2
